[{"chinese": " n. 遗产, 继承物", "eng": "heritage"}, {"chinese": " n. 神,偶像,(God)上帝\nvt. 像对神一样崇拜", "eng": "god"}, {"chinese": " n. 恐怖分子", "eng": "terrorist"}, {"chinese": " adj. 占优势的，主导的，显性的\nn. 主宰者", "eng": "dominant"}, {"chinese": " adv.顺利地,成功地", "eng": "successfully"}, {"chinese": " vt. 拉屎\nn. 粪,屎,讨厌的家伙\ninerj. (骂人的话)狗屁\nadj. 非常糟糕", "eng": "shit"}, {"chinese": " n. 柠檬", "eng": "lemon"}, {"chinese": " adj. 饥饿的，渴望的", "eng": "hungry"}, {"chinese": " n. 侦测, 感官, 感觉; 理智; 意义\nvt. 感觉, 了解; 检测", "eng": "sense"}, {"chinese": " adj. 干的，干燥的,干旱的，不行于色的，枯燥无味的，无酒的，口渴的\nvt. 把...弄干\nvi. （使）变干", "eng": "dry"}, {"chinese": " vt. 闲逛走过\nvi. 游荡,漫步,流浪,蜿蜒曲折,离群失散,走神\nn. 游荡,闲逛,流浪,离群失散", "eng": "wander"}, {"chinese": " vt. 呈送, 递交, 主张\nvt. 使服从, 屈服\nvi. 屈从; 忍受", "eng": "submit"}, {"chinese": " n. 经济学", "eng": "economics"}, {"chinese": " adj. 裸体的,无掩饰的,明白的,手无寸铁的", "eng": "naked"}, {"chinese": " vt. 预期，期望；占先，抢先；提前使用", "eng": "anticipate"}, {"chinese": " n. 坚果,螺母, 螺帽,难对付的人(事)\nvi. 采坚果", "eng": "nut"}, {"chinese": " n. 祖先传下来之物,遗赠物\nadj. [计算机]旧系统的", "eng": "legacy"}, {"chinese": " n. 延长,扩充,范围,分机号码", "eng": "extension"}, {"chinese": " n. 耸肩\nv. 耸肩", "eng": "shrug"}, {"chinese": " n. 电池,一系列,排炮", "eng": "battery"}, {"chinese": " n. 到达,达到,到达者", "eng": "arrival"}, {"chinese": " adj. 合法的, 正当的, 合理的, 世袭的\nvt. 使合法, 授权, 宣布...为合法", "eng": "legitimate"}, {"chinese": " n. 信仰,趋向,定位,适应,情况介绍\n[计算机] 定向", "eng": "orientation"}, {"chinese": " n. 膨胀,通货膨胀", "eng": "inflation"}, {"chinese": " v. (with)竞争,对抗,对付,妥善处理\nvi. 对付,妥善处理", "eng": "cope"}, {"chinese": " n. 火焰,火舌,鲜红色,光辉,恋人,怀念,辱骂信息\nvi. 焚烧,爆发,面红, 发辱骂信息\nvt. 用烟火发信号,用火对待,发辱骂信息", "eng": "flame"}, {"chinese": " n. 串,丛,群\nv. 聚合,成串,丛生,使...聚集", "eng": "cluster"}, {"chinese": " n.[计算机]主机； 主人，东道主； 节目主持人； 酒店业主\nvt.当主人； 主办宴会，主持节目； 款待，做东\nvi.做主人，做东道主", "eng": "host"}, {"chinese": " vbl. 嗅出,吹号角(wind的过去式和过去分词)\r\nn. 创伤,伤害,苦痛\r\nvt. &vi. 伤害", "eng": "wound"}, {"chinese": " adj. 附属的,依赖的,悬垂的\nn. 受经济援助者", "eng": "dependent"}, {"chinese": " n. 阵雨,淋浴\nvi. 倾盆而下,淋浴\nvt. 淋湿,下骤雨,使(大量东西)落在某人身上", "eng": "shower"}, {"chinese": " adj. 制度上的，惯例的，机构的", "eng": "institutional"}, {"chinese": " vt. 描述,描绘", "eng": "depict"}, {"chinese": " vi. 操作, 运转\nvt. 起作用, 动手术", "eng": "operate"}, {"chinese": " n. 肉(体),人性\nvt. 用肉喂,赋予血肉,使长肉\nvi. 变胖", "eng": "flesh"}, {"chinese": " n. 车库, 汽车修理厂\nvt. 把...放入车库", "eng": "garage"}, {"chinese": " n. 操作员,管理者,技工,报务员", "eng": "operator"}, {"chinese": " n. 教师,讲师,指导书", "eng": "instructor"}, {"chinese": " n. 崩溃,倒塌,暴跌\nvi. 倒塌,崩溃,瓦解,折叠\nvt. 倒塌,缩减", "eng": "collapse"}, {"chinese": " v. 借, 借入, 借用", "eng": "borrow"}, {"chinese": " adv. 而且, 此外", "eng": "furthermore"}, {"chinese": " n. 喜剧,滑稽, 幽默事件", "eng": "comedy"}, {"chinese": " vt. 抵押\nn. 抵押；房屋抵押贷款", "eng": "mortgage"}, {"chinese": " n. 核准,处罚,约束力\nv. 制定制裁规则,认许,核准", "eng": "sanction"}, {"chinese": " adj. 平民的\nn. 罗马法专家,平民", "eng": "civilian"}, {"chinese": " adj. 十二,12,12", "eng": "twelve"}, {"chinese": " n. 周刊, 周报\nadj. 每周的, 一周一次的, 周刊的\nadv. 每周, 一周一次", "eng": "weekly"}, {"chinese": " n. (动植物的)产地,栖息地", "eng": "habitat"}, {"chinese": " n. 谷物, 谷类, 颗粒, 细粒, 纹理\nvt. 用谷物喂养, 形成颗粒", "eng": "grain"}, {"chinese": " n. 刷子,画笔,轻擦,小冲突, 灌木丛\nvt. 用刷子清洗,画,拭去,打发\nvi. 轻擦,拂拭", "eng": "brush"}, {"chinese": " n. 意识,知觉,自觉,觉悟", "eng": "consciousness"}, {"chinese": " vt. 投入于,献身", "eng": "devote"}, {"chinese": " vt.破裂，打开； （使…）开裂； 说（笑话）； 开瓶\nvi.断裂，折断； 碎裂声，爆裂声； 镜子破裂了； 失去控制，衰退\nn.裂缝； 试图； 缝隙； （可听到响声的）重击\nadj.训练有素的； 技艺高超的； 优秀的； 一流的", "eng": "crack"}, {"chinese": " n. 测量,衡量,尺寸,大小", "eng": "measurement"}, {"chinese": " n. 省, 范围", "eng": "province"}, {"chinese": " n. 安乐,安逸,悠闲\nvt. 使...安乐,使...安心\nv. 减轻,放松", "eng": "ease"}, {"chinese": " vt. 抓住,攻占,理解,侵袭\nvi. 抓住,卡住,终止", "eng": "seize"}, {"chinese": " n.偶尔,道德规范", "eng": "ethics"}, {"chinese": " n. 提名, 任命, 提名权", "eng": "nomination"}, {"chinese": " n. 同意,许可,允许", "eng": "permission"}, {"chinese": " adj. 明智的,有学问的,有智慧的,聪明的\nn. 方式\nvt. 引导\nvi. 学", "eng": "wise"}, {"chinese": " n. 女演员", "eng": "actress"}, {"chinese": " n. 顶点;最高阶层\nvi. 参加最高级会议,爬到最高点", "eng": "summit"}, {"chinese": " adj. 酸的\nn. 酸, 酸味物质", "eng": "acid"}, {"chinese": " n. 让步,机率,可能性,比率,胜败优劣之别", "eng": "odds"}, {"chinese": " adj. 有天赋的, 有才华的", "eng": "gifted"}, {"chinese": " n. 打破,挫折,顿挫\n[计算机] 失败", "eng": "frustration"}, {"chinese": " n. 媒体, 方法, 媒介\nadj. 适中的, 中等的", "eng": "medium"}, {"chinese": " n. 功能, 函数, 重大聚会\nvi. 运行, 起作用", "eng": "function"}, {"chinese": " adv. 身体上地", "eng": "physically"}, {"chinese": " vt.承认； 同意； 准许； 授予\nn.拨款； 补助金； 授给物（如财产、授地、专有权、补助、拨款等）\nvi.同意", "eng": "grant"}, {"chinese": " vt. 区别,辨认,特别关注\nvi. 区别", "eng": "distinguish"}, {"chinese": " n. 岸,滨,国家,陆地,斜撑柱\nvt. (up)支撑,支持", "eng": "shore"}, {"chinese": " adv. 重复地, 再三地", "eng": "repeatedly"}, {"chinese": " n. 肺,呼吸器官", "eng": "lung"}, {"chinese": " n. 商行,公司\nvt. (使)变得坚实,定案\nvi. 变硬,恢复\nadj. 坚定的,坚固的,结实的\nadv. 稳固地,坚定地", "eng": "firm"}, {"chinese": " n. 跑步;经营,管理\nadj. 奔跑的;流动的;运转中的\nadv. 连续地", "eng": "running"}, {"chinese": " adj. 正确的\nv. 改正,纠正\nvt. 改正", "eng": "correct"}, {"chinese": " adj. (from)独特的,不同的,明显的,清楚的", "eng": "distinct"}, {"chinese": " adj. 艺术的", "eng": "artistic"}, {"chinese": " n. 谈话,演讲\nvi. 谈话,讲述\nvt. 叙述,讨论", "eng": "discourse"}, {"chinese": " n. 篮,篓,筐，篮球筐,得分", "eng": "basket"}, {"chinese": " int. 啊, 哈\n=aah", "eng": "ah"}, {"chinese": " adj.好战的,战斗的", "eng": "fighting"}, {"chinese": " adj. 给人深刻印象的", "eng": "impressive"}, {"chinese": " n. 竞争者,对手", "eng": "competitor"}, {"chinese": " adj. 丑陋的, 难看的", "eng": "ugly"}, {"chinese": " adj. 担心的，烦恼的\n动词worry的过去式和过去分词", "eng": "worried"}, {"chinese": " v. 描写,描写...的肖像,逼真地描写", "eng": "portray"}, {"chinese": " n. 粉,粉末,细雪,火药\nvt. 洒粉于,使变成粉,重击\nvi. 变成粉,涂粉", "eng": "powder"}, {"chinese": " n. 鬼,幽灵,一丝\nvt. &vi. 像(鬼一样)地行进", "eng": "ghost"}, {"chinese": " v. 说服 vt. 劝说,说服", "eng": "persuade"}, {"chinese": " adj. 适度的, 稳健的, 温和的, 中等的\nv. 节制, 使...稳定, 使...缓和\nn. 稳健的人", "eng": "moderate"}, {"chinese": " adj. 随后的,后来的", "eng": "subsequent"}, {"chinese": " adj. 继续的, 延续的\n动词continue的过去式和过去分词", "eng": "continued"}, {"chinese": " n. 饼干", "eng": "cookie"}, {"chinese": " n. 运送者,行李架, 客运公司, 运输工具,航空母舰,带菌者,电信公司", "eng": "carrier"}, {"chinese": " adj. 烹饪的\nn. 烹饪\n动词cook的现在分词", "eng": "cooking"}, {"chinese": " adj. 经常的,频繁的\nvt. 常到,常去", "eng": "frequent"}, {"chinese": " n. 禁令\nv. 禁止\nvt. 禁止,取缔", "eng": "ban"}, {"chinese": " n. 摇摆,改变,冲力\nvt. &vi. 摇摆,旋转,动摇", "eng": "swing"}, {"chinese": " adj. 橙色的\nn. 橘子,橙黄色", "eng": "orange"}, {"chinese": " adj. 可怕的, 畏惧的, 充满敬畏的, 艰难的\nadv. 极其", "eng": "awful"}, {"chinese": " vt. 钦佩, 羡慕, 赞美", "eng": "admire"}, {"chinese": " adj. 宠爱的,珍爱的\nn. 宠物,生气\nvt. 宠爱,抚摸,溺爱\nvi. 拥抱", "eng": "pet"}, {"chinese": " n. 奇迹", "eng": "miracle"}, {"chinese": " vt. 超过, 胜过, 超出界限\nvi. 领先", "eng": "exceed"}, {"chinese": " n. 节奏,韵律", "eng": "rhythm"}, {"chinese": " adj. 分布(或散布)广的,普遍的", "eng": "widespread"}, {"chinese": " n. 谋杀, 杀戮\nadj. 杀害的, 疲惫的, 迷人的\n动词kill的现在分词形式", "eng": "killing"}, {"chinese": " adj. 可爱的,令人愉快的\nn. 漂亮的女人,美好的东西", "eng": "lovely"}, {"chinese": " n. 罪,罪孽,过失\nvi. 犯罪,违反", "eng": "sin"}, {"chinese": " n. 慈善机关(团体),仁慈,宽厚", "eng": "charity"}, {"chinese": " n. 原稿,手稿,脚本\nvi. 写剧本", "eng": "script"}, {"chinese": " n. 战略,策略\nadj. 战术的,有策略的", "eng": "tactic"}, {"chinese": " n. 身份的证明\nn. 视为同一,证明同一,确认", "eng": "identification"}, {"chinese": " n. 转型,转化,改造", "eng": "transformation"}, {"chinese": " adj. 每天的,日常的\nb.平常的日子", "eng": "everyday"}, {"chinese": " n. (pl.)新闻提要, 大字标题", "eng": "headline"}, {"chinese": " v. 撞碎, 猛使...破碎, 迫降，发出巨响\nn. 轰隆声, 猛撞, 崩溃, 破产, 垮台\nadj. 速成的\nn. 粗布", "eng": "crash"}, {"chinese": " n. 冒险,风险,投机\nvt. 敢尝试,谨慎地做，冒险一试\nvi. 冒险做", "eng": "venture"}, {"chinese": " n. 侵入, 侵略", "eng": "invasion"}, {"chinese": " adj.军事的；军用的；讨厌的；好战的\nn.军人；军队；武装力量", "eng": "military"}, {"chinese": " adv. 尽管如此(仍然)\nconj. 尽管如此(仍然)", "eng": "nonetheless"}, {"chinese": " adj. 足够的, 充足的, 适当的, 能胜任的", "eng": "adequate"}, {"chinese": " n. 钢琴\nadj. &adv. 轻柔的", "eng": "piano"}, {"chinese": " n. 杂货店", "eng": "grocery"}, {"chinese": " n. 激烈,强度,强烈,剧烈", "eng": "intensity"}, {"chinese": " adj.高的,轻微变质的,高尚的,严重的,强的\nadv. 高,好\nn. 高地,天堂,高气压,高度,兴奋", "eng": "high"}, {"chinese": " n. 毛毯,覆盖物,排字版\nvt. 用毯子裹,扑灭,挡风,覆盖,使包含\nadj. 包含所有的,适用于所有情形的", "eng": "blanket"}, {"chinese": " n. 差额,利润,页边空白,边缘\nvt. 使围绕于,加边缘", "eng": "margin"}, {"chinese": " adj. 主要的\nn. 负责人, 校长, 资本", "eng": "principal"}, {"chinese": " vt. 操纵，对...发号施令\nn. (橄榄球赛中指挥反攻的)四分卫\nvi. 打四分卫", "eng": "quarterback"}, {"chinese": " n. 老鼠,鼠标，胆小如鼠的人，乌青色的肿块\nvi. 捕鼠，蹑手蹑脚行动\nvt. 仔细寻找", "eng": "mouse"}, {"chinese": " n. 绳，绳索\nvt. 捆，绑\nvi. 拧成绳状", "eng": "rope"}, {"chinese": " n. 水泥,混凝土\nadj. 具体的,实在的,水泥的\nvt. &vi. 凝结,结合", "eng": "concrete"}, {"chinese": " n. 药方, 对策, 开处方", "eng": "prescription"}, {"chinese": " n. 追求,狩猎\nv. 追捕,追逐,在金属上打花样", "eng": "chase"}, {"chinese": " n. 文件,公文\nvt. 记载,用文件等证明\n[计算机] 文档", "eng": "document"}, {"chinese": " adj. 砖似的\nn. 砖\nv. 用砖围砌,用砖填补\nvt. (up)用砖砌,用砖堵住", "eng": "brick"}, {"chinese": " n. 招聘,新兵,新成员\nvt.&vi. 恢复,补充,徵募", "eng": "recruit"}, {"chinese": " n. 片,补丁,碎片\nvt. 补缀,掩饰,平息", "eng": "patch"}, {"chinese": " n. 共识，一致，合意\nn. [生理]交感", "eng": "consensus"}, {"chinese": " adj. 恐怖的,令人毛骨悚然的\nn. 恐怖,战栗,厌恶", "eng": "horror"}, {"chinese": " n. 录音\n动词record的现在分词", "eng": "recording"}, {"chinese": " n. 画家", "eng": "painter"}, {"chinese": " adj. 殖民地的\nn. 殖民地居民", "eng": "colonial"}, {"chinese": " n.饼图 n.派, 馅饼, 杂乱, 喜鹊, 爱说话的人 vt.弄乱", "eng": "pie"}, {"chinese": " n. 缘故, 利益, 好处", "eng": "sake"}, {"chinese": " 加沙(西南亚地中海岸港市, 巴勒斯坦的一部分, 1967年被以色列占领)", "eng": "Gaza"}, {"chinese": " n. 勇气", "eng": "courage"}, {"chinese": " n. 怀孕", "eng": "pregnancy"}, {"chinese": " n. 发誓, 誓言\nvt. &vi. 发誓, 宣誓, 咒骂", "eng": "swear"}, {"chinese": " n. 败北,失败\nvt. 击败", "eng": "defeat"}, {"chinese": " n. 线索\nvt. 提示", "eng": "clue"}, {"chinese": " vt. 加强，加固；强化；补充\nvi. 求援；得到增援；给予更多的支持\nn. 加强；加固物；加固材料", "eng": "reinforce"}, {"chinese": " n. 胜利\nvi. 胜利,成功\nvt. 赢得,战胜", "eng": "win"}, {"chinese": " n. 混乱,混淆,不确定状态", "eng": "confusion"}, {"chinese": " n. 薄的切片,一部份,锅铲\nvt. 切成薄片,大幅降低", "eng": "slice"}, {"chinese": " n. 职业", "eng": "occupation"}, {"chinese": " adj. 严重的,珍贵的,亲爱的,昂贵的,衷心的\nadv. 高价地,热爱地\nn. 亲爱的人,可爱的人\nint. 啊,哎呀", "eng": "dear"}, {"chinese": " n. 煤, 木炭, 运煤工\nvt. 烧成炭,供应煤\nvi. 装煤, 加煤", "eng": "coal"}, {"chinese": " adj. 神圣的,受尊重的", "eng": "sacred"}, {"chinese": " adj. 犯罪的, 刑事的, 无耻的\nn. 罪犯", "eng": "criminal"}, {"chinese": " n.   公式,配方,规则；代乳品\nadj. （赛车的）级的，方程式的", "eng": "formula"}, {"chinese": " adj. 认知的,认识的,有认识力的", "eng": "cognitive"}, {"chinese": " adj. 集体的,共同的\nn. 集体", "eng": "collective"}, {"chinese": " adj. 精确的\nvt. 强求,要求,索取", "eng": "exact"}, {"chinese": " n. 伯, 姑父, 舅, 叔, 姨父", "eng": "uncle"}, {"chinese": " n. 正方形,街区,平方，广场\nadj. 正方形的,正直的,公正的,结实的\nvt. 使...成方形,调整，一致\nvi. 符合\nadv. 成直角,直接的,正方形地", "eng": "square"}, {"chinese": " n. 船长, 队长, 首领\nvt. 率领, 指挥", "eng": "captain"}, {"chinese": " n. 呼吸，叹息（带有情感）\nvi. 发出叹息的声音，感叹\nvt. 叹息", "eng": "sigh"}, {"chinese": " n. 属性, 特征; 标志, 象征\nvt. 归于, 属于", "eng": "attribute"}, {"chinese": " n. 敢, 挑战\naux. 敢\nvi. 敢\nvt. 敢于, 勇于面对", "eng": "dare"}, {"chinese": " n.认可，同意\nv.赞成或同意； 批准\nint.行，用以表达准许或同意之意\nadj.可以，不错", "eng": "okay"}, {"chinese": " adj. 无家可归的", "eng": "homeless"}, {"chinese": " adj. 凉的,凉快的,冷静的,冷色系的\nadv. 冷静地\nn. 凉快\nvt. &vi. (使)变凉,(使)冷静", "eng": "cool"}, {"chinese": " n. 厨房(长方形炉)", "eng": "galley"}, {"chinese": " n. 英式足球", "eng": "soccer"}, {"chinese": " n. 被告", "eng": "defendant"}, {"chinese": " n. 隧道,地下道\nv. 挖隧道", "eng": "tunnel"}, {"chinese": " n. 适合度（生物学术语）\nn. 健康", "eng": "fitness"}, {"chinese": " n. 下摆,膝盖,舐声,一周\nvt. 包围, 抱...在膝上, 重叠, 舔, 拍打, 泼溅\nvi. 重叠, 围住, 轻拍, 舔", "eng": "lap"}, {"chinese": " adj.重大的，重要的； 严重的； [音乐]沉重的； （颜色等）朴素的\nadv.沉重地，庄重地； 极慢地\nn.坟墓，墓穴； 埋葬…的地方； 下场； 死亡\nvt.雕刻； 铭记", "eng": "grave"}, {"chinese": " n. 脚趾,足尖\nvt. 趾触,趾踢\nvi. 踮着脚尖走", "eng": "toe"}, {"chinese": " n. 容器, 集装箱", "eng": "container"}, {"chinese": " n. 美德,优点;贞操", "eng": "virtue"}, {"chinese": " adj. 在国外,海外(一般作表语)\nadv. 到国外, 广为流传", "eng": "abroad"}, {"chinese": " n. 建筑师", "eng": "architect"}, {"chinese": " adv.戏剧地,引人注目地", "eng": "dramatically"}, {"chinese": " n. 组成(接通, 补给, 修理), 化妆品", "eng": "makeup"}, {"chinese": " n. 打听, 询问, 调查, 查问\n=enquiry(英)", "eng": "inquiry"}, {"chinese": " n. 玫瑰,蔷薇\nv. (rise的过去式) 起立,上升,升起\nadj. 玫瑰色的,玫瑰的", "eng": "rose"}, {"chinese": " adv. 惊人地(意外地)", "eng": "surprisingly"}, {"chinese": " n. 加亮区,精彩部分, 最重要的细节或事件, 闪光点\nvt. 加亮,强调, 使...显得重要, 照亮\n[计算机] 醒目", "eng": "highlight"}, {"chinese": " n. 减少(量),降低\nvt.& vi. 减少,降低", "eng": "decrease"}]